iPat/__init__.py
iPat-0.0.dist-info/LICENSE
iPat-0.0.dist-info/METADATA
iPat-0.0.dist-info/WHEEL
iPat-0.0.dist-info/top_level.txt
iPat-0.0.dist-info/RECORD
