Metadata-Version: 2.1
Name: iPat
Version: 0.0
Summary: Python version of iPat
Home-page: https://github.com/Zhiwu-Zhang-Lab/James_Git
Author: James Chen
Author-email: chun-peng.chen@wsu.edu
License: MIT
Platform: UNKNOWN
Requires-Dist: numpy (>=1.11)
Requires-Dist: matplotlib (>=1.5)
